cv2_helper/__init__.py
cv2_helper/utils/__init__.py
cv2_helper/utils/draw.py
cv2_helper-0.0.7.dist-info/METADATA
cv2_helper-0.0.7.dist-info/WHEEL
cv2_helper-0.0.7.dist-info/top_level.txt
cv2_helper-0.0.7.dist-info/RECORD
