Metadata-Version: 2.1
Name: cv2-helper
Version: 0.0.7
Summary: cv2 helper
Home-page: https://github.com/automatethem/cv2-helper
Author: Sang Ki Kwon
Author-email: automatethem@gmail.com
License: MIT
Platform: UNKNOWN
